trooper/__init__.py
trooper/base.py
trooper/node.py
trooper/server.py
trooper-0.0.1.dist-info/LICENSE
trooper-0.0.1.dist-info/METADATA
trooper-0.0.1.dist-info/WHEEL
trooper-0.0.1.dist-info/top_level.txt
trooper-0.0.1.dist-info/RECORD
